arfs_gen/__init__.py
arfs_gen/gen_data.py
arfs_gen/gen_lupi.py
arfs_gen/tests/__init__.py
arfs_gen/tests/test_toydata.py
arfs_gen-1.2.1.dist-info/LICENSE
arfs_gen-1.2.1.dist-info/METADATA
arfs_gen-1.2.1.dist-info/WHEEL
arfs_gen-1.2.1.dist-info/RECORD
