Metadata-Version: 2.3
Name: arfs_gen
Version: 1.2.1
Summary: Library to generate toy data for machine learning experiments in the context of all-relevant feature selection.
License: MIT
Keywords: data generation,toy data,all-relevant feature selection,machine learning
Author: Lukas Pfannschmidt
Author-email: lukas@lpfann.me
Requires-Python: >=3.9,<4.0
Classifier: License :: OSI Approved :: MIT License
Classifier: Programming Language :: Python :: 3
Classifier: Programming Language :: Python :: 3.9
Classifier: Programming Language :: Python :: 3.10
Classifier: Programming Language :: Python :: 3.11
Classifier: Programming Language :: Python :: 3.12
Classifier: Programming Language :: Python :: 3.13
Requires-Dist: numpy (>=1.21.0,<2.0.0)
Requires-Dist: scikit-learn (>=1.0.0,<2.0.0)
Project-URL: Repository, https://github.com/lpfann/arfs_gen
